[
  {
    "name": "Adventurer",
    "description": "A man on an adventure.",
    "stats":
    {
      "ATHLETICS":    3,
      "INTELLIGENCE": 3,
      "WILLPOWER":    3
    },
    "gear":
    [
      {
        "name": "Rusty Sword",
        "aptitude": "ATHLETICS",
        "modifiers":
        [
          {
            "stat": "FATIGUE",
            "value": 1,
            "dice": "d4"
          }
        ]
      }
    ]
  },
  {
    "name": "Amateur Guard",
    "description": "A simple guard with shabby equipment.",
    "stats":
    {
      "ATHLETICS":    3,
      "INTELLIGENCE": 3,
      "WILLPOWER":    3
    },
    "gear":
    [
      {
        "name": "Dull Spear",
        "aptitude": "ATHLETICS",
        "modifiers":
        [
          {
            "stat": "FATIGUE",
            "value": 1,
            "dice": "d4"
          }
        ]
      },
      {
      "name": "Cumbersome Chainmail",
      "modifiers":
      [
        {
          "stat": "DEFENCE",
          "value": 2
        },
        {
          "stat": "ATHLETICS",
          "value": -1
        }
      ]
    }
    ]
  },
  {
    "name": "Novice Sorcerer",
    "description": "A man studying the fabric of what makes the world.",
    "stats":
    {
      "ATHLETICS":    1,
      "INTELLIGENCE": 3,
      "WILLPOWER":    4
    },
    "gear":
    [
      {
        "name": "Flame Spell",
        "aptitude": "WILLPOWER",
        "modifiers":
        [
          {
            "stat": "FATIGUE",
            "value": 2,
            "dice": "d4"
          }
        ]
      },
      {
        "name": "Spellbook",
        "modifiers":
        [
          {
            "stat": "WILLPOWER",
            "value": 1
          },
          {
            "stat": "INTELLIGENCE",
            "value": -1
          }
        ]
      }
    ]
  },
  {
    "name": "Wolf",
    "description": "A feral wolf, with dark fur.",
    "stats":
    {
      "ATHLETICS":    3,
      "INTELLIGENCE": 2,
      "WILLPOWER":    2
    },
    "gear":
    [
      {
        "name": "Claws",
        "aptitude": "ATHLETICS",
        "modifiers":
        [
          {
            "stat": "FATIGUE",
            "value": 1,
            "dice": "d4"
          }
        ]
      }
    ]
  },
  {
    "name": "Bear",
    "description": "A feral bear, with brown fur.",
    "stats":
    {
      "ATHLETICS":    5,
      "INTELLIGENCE": 2,
      "WILLPOWER":    3
    },
    "gear":
    [
      {
        "name": "Claws",
        "aptitude": "ATHLETICS",
        "modifiers":
        [
          {
            "stat": "FATIGUE",
            "value": 2,
            "dice": "d4"
          }
        ]
      }
    ]
  }
]